dblog/__init__.py
dblog/admin.py
dblog/apps.py
dblog/loguru_db_handler.py
dblog/middleware.py
dblog/models.py
dblog/migrations/__init__.py
migrations/__init__.py
django_logging_into_db-0.0.2.dist-info/LICENSE
django_logging_into_db-0.0.2.dist-info/METADATA
django_logging_into_db-0.0.2.dist-info/WHEEL
django_logging_into_db-0.0.2.dist-info/top_level.txt
django_logging_into_db-0.0.2.dist-info/RECORD
