Metadata-Version: 2.1
Name: django-logging-into-db
Version: 0.0.2
Summary: Log http errors or custom logs with loguru library into db
Home-page: https://github.com/shoytov/django-dblog
Author: Dmitry Shoytov
Author-email: shoytov@gmail.com
License: UNKNOWN
Platform: UNKNOWN
Classifier: Programming Language :: Python :: 3
Classifier: License :: OSI Approved :: MIT License
Classifier: Operating System :: OS Independent
Requires-Python: >=3.6
Requires-Dist: loguru
